metaflowbot/__init__.py
metaflowbot/__main__.py
metaflowbot/action_loader.py
metaflowbot/cli.py
metaflowbot/exceptions.py
metaflowbot/rules.py
metaflowbot/server.py
metaflowbot/slack_client.py
metaflowbot/state.py
metaflowbot/version.py
metaflowbot/actions/__init__.py
metaflowbot/actions/basic/__init__.py
metaflowbot/actions/basic/commands.py
metaflowbot/actions/basic/rules.yml
metaflowbot/actions/runs/__init__.py
metaflowbot/actions/runs/commands.py
metaflowbot/actions/runs/rules.yml
metaflowbot/actions/runs/run_resolver.py
metaflowbot/message_templates/__init__.py
metaflowbot/message_templates/templates.py
metaflowbot-1.0.3.dist-info/LICENSE
metaflowbot-1.0.3.dist-info/METADATA
metaflowbot-1.0.3.dist-info/WHEEL
metaflowbot-1.0.3.dist-info/entry_points.txt
metaflowbot-1.0.3.dist-info/top_level.txt
metaflowbot-1.0.3.dist-info/RECORD
