Metadata-Version: 2.1
Name: metaflowbot
Version: 1.0.3
Summary: UNKNOWN
Home-page: https://github.com/outerbounds/metaflowbot
Author: Outerbounds
License: Apache License 2.0
Platform: UNKNOWN
Requires-Python: >=3.6
Requires-Dist: metaflow (>=2.4.0)
Requires-Dist: timeago (==1.0.15)
Requires-Dist: pyyaml (==5.4.1)
Requires-Dist: slack-sdk (==3.7.0)
Requires-Dist: requests
